s3plz/__init__.py
s3plz/utils.py
s3plz-0.1.7.dist-info/DESCRIPTION.rst
s3plz-0.1.7.dist-info/METADATA
s3plz-0.1.7.dist-info/RECORD
s3plz-0.1.7.dist-info/WHEEL
s3plz-0.1.7.dist-info/metadata.json
s3plz-0.1.7.dist-info/top_level.txt
