Metadata-Version: 2.0
Name: s3plz
Version: 0.1.7
Summary: A polite interface for sending python objects to and from Amazon S3.
Home-page: https://github.com/enigma-io/s3plz
Author: Brian Abelson
Author-email: brian@enigma.io
License: MIT
Keywords: s3,aws
Platform: UNKNOWN
Classifier: Development Status :: 3 - Alpha
Classifier: Topic :: Communications :: Email
Classifier: License :: OSI Approved :: MIT License
Requires-Dist: boto
Requires-Dist: python-dateutil
Requires-Dist: pytz
